fitness_influencer_mcp/__init__.py
fitness_influencer_mcp/comment_categorizer.py
fitness_influencer_mcp/content_calendar.py
fitness_influencer_mcp/cross_platform_optimizer.py
fitness_influencer_mcp/grok_image_gen.py
fitness_influencer_mcp/revenue_analytics.py
fitness_influencer_mcp/server.py
fitness_influencer_mcp/video_jumpcut.py
fitness_influencer_mcp/workout_plan_generator.py
fitness_influencer_mcp-1.3.0.dist-info/METADATA
fitness_influencer_mcp-1.3.0.dist-info/WHEEL
fitness_influencer_mcp-1.3.0.dist-info/entry_points.txt
fitness_influencer_mcp-1.3.0.dist-info/RECORD
