Metadata-Version: 2.4
Name: fitness-influencer-mcp
Version: 1.3.0
Summary: Fitness content creator tools: video editing, AI images, comment management, content calendars.
Project-URL: Homepage, https://github.com/MarceauSolutions/dev-sandbox/tree/main/projects/fitness-influencer
Project-URL: Repository, https://github.com/MarceauSolutions/dev-sandbox
Author-email: "William Marceau Jr." <william@marceausolutions.com>
License-Expression: MIT
Keywords: content,creator,fitness,influencer,mcp,video
Classifier: Development Status :: 4 - Beta
Classifier: Intended Audience :: Developers
Classifier: License :: OSI Approved :: MIT License
Classifier: Programming Language :: Python :: 3
Classifier: Programming Language :: Python :: 3.8
Classifier: Programming Language :: Python :: 3.9
Classifier: Programming Language :: Python :: 3.10
Classifier: Programming Language :: Python :: 3.11
Classifier: Programming Language :: Python :: 3.12
Requires-Python: >=3.8
Requires-Dist: mcp>=1.0.0
Requires-Dist: python-dotenv>=1.0.0
Requires-Dist: requests>=2.28.0
